xdump/__init__.py
xdump/_compat.py
xdump/base.py
xdump/logging.py
xdump/postgresql.py
xdump/sqlite.py
xdump/utils.py
xdump/cli/__init__.py
xdump/cli/base.py
xdump/cli/dump.py
xdump/cli/load.py
xdump/cli/utils.py
xdump/extra/__init__.py
xdump/extra/django/__init__.py
xdump/extra/django/apps.py
xdump/extra/django/xdump/__init__.py
xdump/extra/django/xdump/management/__init__.py
xdump/extra/django/xdump/management/core.py
xdump/extra/django/xdump/management/commands/__init__.py
xdump/extra/django/xdump/management/commands/xdump.py
xdump/extra/django/xdump/management/commands/xload.py
xdump-0.6.0.dist-info/METADATA
xdump-0.6.0.dist-info/RECORD
xdump-0.6.0.dist-info/WHEEL
xdump-0.6.0.dist-info/entry_points.txt
xdump-0.6.0.dist-info/top_level.txt
