Metadata-Version: 2.1
Name: xdump
Version: 0.6.0
Summary: Consistent partial database dump utility
Home-page: https://github.com/Stranger6667/xdump
Author: Dmitry Dygalo
Author-email: dadygalo@gmail.com
Maintainer: Dmitry Dygalo
Maintainer-email: dadygalo@gmail.com
License: MIT
Keywords: database,dump,postgresql
Platform: UNKNOWN
Classifier: Development Status :: 4 - Beta
Classifier: Environment :: Console
Classifier: Intended Audience :: Developers
Classifier: Operating System :: OS Independent
Classifier: License :: OSI Approved :: MIT License
Classifier: Programming Language :: Python
Classifier: Programming Language :: Python :: 3
Classifier: Programming Language :: Python :: 3.4
Classifier: Programming Language :: Python :: 3.5
Classifier: Programming Language :: Python :: 3.6
Classifier: Programming Language :: Python :: 3.7
Classifier: Programming Language :: Python :: Implementation :: CPython
Provides-Extra: django
Requires-Dist: attrs (<19)
Requires-Dist: psycopg2 (<2.8)
Requires-Dist: click (<7)
Provides-Extra: django
Requires-Dist: django (>=1.11); extra == 'django'
